[
  {
    "experiment": "utooth_10f_v1",
    "n_folds": 10,
    "metrics": {
      "corrected_iou": {
        "mean": 0.7334320227305093,
        "std": 0.11247936576304148,
        "min": 0.42475295066833496,
        "max": 0.8292516867319742
      },
      "dice": {
        "mean": 0.8151371786991757,
        "std": 0.11047462187065359,
        "min": 0.5122393071651459,
        "max": 0.9044835766156515
      },
      "binary_iou": {
        "mean": 0.7384538014729818,
        "std": 0.12253154595986211,
        "min": 0.39219574133555096,
        "max": 0.8300682107607523
      },
      "old_accuracy": {
        "mean": 0.5824250161647797,
        "std": 0.05021196301447901,
        "min": 0.5215674936771393,
        "max": 0.6713661551475525
      }
    },
    "fold_results": [
      {
        "fold_idx": 0,
        "checkpoint": "utooth-epoch=27-val_loss=0.4822.ckpt",
        "val_loss": 0.46079198519388836,
        "old_accuracy": 0.5215674936771393,
        "corrected_iou": 0.42475295066833496,
        "dice": 0.5122393071651459,
        "binary_iou": 0.39219574133555096,
        "original_reported_accu": null,
        "original_reported_loss": 0.4822363257408142
      },
      {
        "fold_idx": 1,
        "checkpoint": "utooth-epoch=38-val_loss=0.1030.ckpt",
        "val_loss": 0.09785664081573486,
        "old_accuracy": 0.5964747667312622,
        "corrected_iou": 0.8292516867319742,
        "dice": 0.9044835766156515,
        "binary_iou": 0.8300682107607523,
        "original_reported_accu": null,
        "original_reported_loss": 0.10295838117599487
      },
      {
        "fold_idx": 2,
        "checkpoint": "utooth-epoch=47-val_loss=0.1092.ckpt",
        "val_loss": 0.1066214640935262,
        "old_accuracy": 0.6212934851646423,
        "corrected_iou": 0.7881370981534322,
        "dice": 0.863400936126709,
        "binary_iou": 0.8193251689275106,
        "original_reported_accu": null,
        "original_reported_loss": 0.1092149019241333
      },
      {
        "fold_idx": 3,
        "checkpoint": "utooth-epoch=42-val_loss=0.1471.ckpt",
        "val_loss": 0.15688888231913248,
        "old_accuracy": 0.5851118961970011,
        "corrected_iou": 0.6969730158646902,
        "dice": 0.7600975732008616,
        "binary_iou": 0.7453156510988871,
        "original_reported_accu": null,
        "original_reported_loss": 0.14714449644088745
      },
      {
        "fold_idx": 4,
        "checkpoint": "utooth-epoch=40-val_loss=0.1133.ckpt",
        "val_loss": 0.12866548697153726,
        "old_accuracy": 0.556546668211619,
        "corrected_iou": 0.7860510945320129,
        "dice": 0.8498068253199259,
        "binary_iou": 0.7790758411089579,
        "original_reported_accu": null,
        "original_reported_loss": 0.11331725120544434
      },
      {
        "fold_idx": 5,
        "checkpoint": "utooth-epoch=45-val_loss=0.1694.ckpt",
        "val_loss": 0.19844428698221842,
        "old_accuracy": 0.5281728307406107,
        "corrected_iou": 0.6754747033119202,
        "dice": 0.771259625752767,
        "binary_iou": 0.6842992305755615,
        "original_reported_accu": null,
        "original_reported_loss": 0.16939300298690796
      },
      {
        "fold_idx": 6,
        "checkpoint": "utooth-epoch=42-val_loss=0.1304.ckpt",
        "val_loss": 0.12548931439717612,
        "old_accuracy": 0.6554712057113647,
        "corrected_iou": 0.7872544129689535,
        "dice": 0.8778048356374105,
        "binary_iou": 0.7844424247741699,
        "original_reported_accu": null,
        "original_reported_loss": 0.13035434484481812
      },
      {
        "fold_idx": 7,
        "checkpoint": "utooth-epoch=46-val_loss=0.1095.ckpt",
        "val_loss": 0.11051231622695923,
        "old_accuracy": 0.6713661551475525,
        "corrected_iou": 0.7991816401481628,
        "dice": 0.8746187289555868,
        "binary_iou": 0.806576689084371,
        "original_reported_accu": null,
        "original_reported_loss": 0.10945147275924683
      },
      {
        "fold_idx": 8,
        "checkpoint": "utooth-epoch=28-val_loss=0.1147.ckpt",
        "val_loss": 0.11503255367279053,
        "old_accuracy": 0.5442370772361755,
        "corrected_iou": 0.7976205348968506,
        "dice": 0.8861417472362518,
        "binary_iou": 0.80099818110466,
        "original_reported_accu": null,
        "original_reported_loss": 0.11470407247543335
      },
      {
        "fold_idx": 9,
        "checkpoint": "utooth-epoch=32-val_loss=0.1551.ckpt",
        "val_loss": 0.1558123528957367,
        "old_accuracy": 0.5440085828304291,
        "corrected_iou": 0.7496230900287628,
        "dice": 0.8515186309814453,
        "binary_iou": 0.7422408759593964,
        "original_reported_accu": null,
        "original_reported_loss": 0.15508151054382324
      }
    ]
  },
  {
    "experiment": "utooth_10f_v2",
    "n_folds": 10,
    "metrics": {
      "corrected_iou": {
        "mean": 0.7366055250167847,
        "std": 0.06979679191884149,
        "min": 0.6061717371145884,
        "max": 0.8229867418607076
      },
      "dice": {
        "mean": 0.8240351945161819,
        "std": 0.06753603949762874,
        "min": 0.7062548200289408,
        "max": 0.9013995925585429
      },
      "binary_iou": {
        "mean": 0.7466399987538656,
        "std": 0.0642165262777087,
        "min": 0.6136308709780375,
        "max": 0.814545214176178
      },
      "old_accuracy": {
        "mean": 0.5765364090601602,
        "std": 0.048733925940681884,
        "min": 0.5078398585319519,
        "max": 0.6809104879697164
      }
    },
    "fold_results": [
      {
        "fold_idx": 0,
        "checkpoint": "utooth-epoch=44-val_loss=0.1719.ckpt",
        "val_loss": 0.16309932867685953,
        "old_accuracy": 0.6081969340642294,
        "corrected_iou": 0.7019820809364319,
        "dice": 0.7760568062464396,
        "binary_iou": 0.7362721761067709,
        "original_reported_accu": null,
        "original_reported_loss": 0.17189770936965942
      },
      {
        "fold_idx": 1,
        "checkpoint": "utooth-epoch=25-val_loss=0.1176.ckpt",
        "val_loss": 0.11507896582285564,
        "old_accuracy": 0.5576105912526449,
        "corrected_iou": 0.8229867418607076,
        "dice": 0.9013995925585429,
        "binary_iou": 0.8083269397417704,
        "original_reported_accu": null,
        "original_reported_loss": 0.11756467819213867
      },
      {
        "fold_idx": 2,
        "checkpoint": "utooth-epoch=21-val_loss=0.3253.ckpt",
        "val_loss": 0.30095277229944867,
        "old_accuracy": 0.5334494709968567,
        "corrected_iou": 0.6323768595854441,
        "dice": 0.7167577147483826,
        "binary_iou": 0.6136308709780375,
        "original_reported_accu": null,
        "original_reported_loss": 0.3252643346786499
      },
      {
        "fold_idx": 3,
        "checkpoint": "utooth-epoch=44-val_loss=0.1542.ckpt",
        "val_loss": 0.16141106685002646,
        "old_accuracy": 0.5707571307818095,
        "corrected_iou": 0.7509100039800009,
        "dice": 0.8325803478558859,
        "binary_iou": 0.7488258282343546,
        "original_reported_accu": null,
        "original_reported_loss": 0.15417474508285522
      },
      {
        "fold_idx": 4,
        "checkpoint": "utooth-epoch=49-val_loss=0.1106.ckpt",
        "val_loss": 0.10818580786387126,
        "old_accuracy": 0.5963995655377706,
        "corrected_iou": 0.808355470498403,
        "dice": 0.892634113629659,
        "binary_iou": 0.8107112646102905,
        "original_reported_accu": null,
        "original_reported_loss": 0.1106368899345398
      },
      {
        "fold_idx": 5,
        "checkpoint": "utooth-epoch=38-val_loss=0.1226.ckpt",
        "val_loss": 0.14146173000335693,
        "old_accuracy": 0.5657548308372498,
        "corrected_iou": 0.7692554791768392,
        "dice": 0.8645122845967611,
        "binary_iou": 0.8030734856923422,
        "original_reported_accu": null,
        "original_reported_loss": 0.12263840436935425
      },
      {
        "fold_idx": 6,
        "checkpoint": "utooth-epoch=49-val_loss=0.1060.ckpt",
        "val_loss": 0.10766537984212239,
        "old_accuracy": 0.6809104879697164,
        "corrected_iou": 0.8118801911671957,
        "dice": 0.8954735398292542,
        "binary_iou": 0.814545214176178,
        "original_reported_accu": null,
        "original_reported_loss": 0.10595136880874634
      },
      {
        "fold_idx": 7,
        "checkpoint": "utooth-epoch=30-val_loss=0.2015.ckpt",
        "val_loss": 0.2216127316157023,
        "old_accuracy": 0.5256483356157938,
        "corrected_iou": 0.6061717371145884,
        "dice": 0.7062548200289408,
        "binary_iou": 0.6605280439058939,
        "original_reported_accu": null,
        "original_reported_loss": 0.20147430896759033
      },
      {
        "fold_idx": 8,
        "checkpoint": "utooth-epoch=49-val_loss=0.1454.ckpt",
        "val_loss": 0.15466630458831787,
        "old_accuracy": 0.6187968850135803,
        "corrected_iou": 0.7270342409610748,
        "dice": 0.8131852447986603,
        "binary_iou": 0.7403721213340759,
        "original_reported_accu": null,
        "original_reported_loss": 0.1453680396080017
      },
      {
        "fold_idx": 9,
        "checkpoint": "utooth-epoch=31-val_loss=0.1688.ckpt",
        "val_loss": 0.1693061888217926,
        "old_accuracy": 0.5078398585319519,
        "corrected_iou": 0.7351024448871613,
        "dice": 0.8414974808692932,
        "binary_iou": 0.7301140427589417,
        "original_reported_accu": null,
        "original_reported_loss": 0.16877543926239014
      }
    ]
  },
  {
    "experiment": "utooth_10f_v3",
    "n_folds": 10,
    "metrics": {
      "corrected_iou": {
        "mean": 0.7422166188557943,
        "std": 0.08677838281448105,
        "min": 0.5814139346281687,
        "max": 0.8503597180048624
      },
      "dice": {
        "mean": 0.824465634425481,
        "std": 0.08117897430605729,
        "min": 0.6801064411799113,
        "max": 0.918658971786499
      },
      "binary_iou": {
        "mean": 0.7463359077771505,
        "std": 0.08831546659718129,
        "min": 0.5747227172056834,
        "max": 0.8530414899190267
      },
      "old_accuracy": {
        "mean": 0.5813875257968902,
        "std": 0.03857503587806204,
        "min": 0.547157088915507,
        "max": 0.6737412611643473
      }
    },
    "fold_results": [
      {
        "fold_idx": 0,
        "checkpoint": "utooth-epoch=56-val_loss=0.1157.ckpt",
        "val_loss": 0.13189548254013062,
        "old_accuracy": 0.5534615914026896,
        "corrected_iou": 0.7696869174639384,
        "dice": 0.8654585878054301,
        "binary_iou": 0.784229556719462,
        "original_reported_accu": 0.5733702778816223,
        "original_reported_loss": 0.11569708585739136
      },
      {
        "fold_idx": 1,
        "checkpoint": "utooth-epoch=48-val_loss=0.1038.ckpt",
        "val_loss": 0.11169075965881348,
        "old_accuracy": 0.5965627431869507,
        "corrected_iou": 0.7840065558751425,
        "dice": 0.8595775961875916,
        "binary_iou": 0.8117179870605469,
        "original_reported_accu": 0.7142395973205566,
        "original_reported_loss": 0.10382556915283203
      },
      {
        "fold_idx": 2,
        "checkpoint": "utooth-epoch=47-val_loss=0.3371.ckpt",
        "val_loss": 0.30342717965443927,
        "old_accuracy": 0.5761333902676901,
        "corrected_iou": 0.6098512709140778,
        "dice": 0.6828824281692505,
        "binary_iou": 0.5747227172056834,
        "original_reported_accu": 0.6028931140899658,
        "original_reported_loss": 0.3371087908744812
      },
      {
        "fold_idx": 3,
        "checkpoint": "utooth-epoch=60-val_loss=0.1457.ckpt",
        "val_loss": 0.16293559471766153,
        "old_accuracy": 0.5714109937349955,
        "corrected_iou": 0.7171667218208313,
        "dice": 0.8155601819356283,
        "binary_iou": 0.7276390989621481,
        "original_reported_accu": 0.5775966048240662,
        "original_reported_loss": 0.14574068784713745
      },
      {
        "fold_idx": 4,
        "checkpoint": "utooth-epoch=43-val_loss=0.2227.ckpt",
        "val_loss": 0.25349167982737225,
        "old_accuracy": 0.5597098072369894,
        "corrected_iou": 0.5814139346281687,
        "dice": 0.6801064411799113,
        "binary_iou": 0.6089652379353842,
        "original_reported_accu": 0.5786515474319458,
        "original_reported_loss": 0.22266773879528046
      },
      {
        "fold_idx": 5,
        "checkpoint": "utooth-epoch=49-val_loss=0.1542.ckpt",
        "val_loss": 0.19517050186793009,
        "old_accuracy": 0.547157088915507,
        "corrected_iou": 0.6848898132642111,
        "dice": 0.7791818181673685,
        "binary_iou": 0.6978928744792938,
        "original_reported_accu": 0.6060528755187988,
        "original_reported_loss": 0.15422552824020386
      },
      {
        "fold_idx": 6,
        "checkpoint": "utooth-epoch=57-val_loss=0.1025.ckpt",
        "val_loss": 0.12085904677708943,
        "old_accuracy": 0.6266064445177714,
        "corrected_iou": 0.7864286700884501,
        "dice": 0.8501614928245544,
        "binary_iou": 0.791323184967041,
        "original_reported_accu": 0.6597135066986084,
        "original_reported_loss": 0.10245311260223389
      },
      {
        "fold_idx": 7,
        "checkpoint": "utooth-epoch=61-val_loss=0.0844.ckpt",
        "val_loss": 0.08108842372894287,
        "old_accuracy": 0.6737412611643473,
        "corrected_iou": 0.8503597180048624,
        "dice": 0.918658971786499,
        "binary_iou": 0.8530414899190267,
        "original_reported_accu": 0.6768726706504822,
        "original_reported_loss": 0.08439582586288452
      },
      {
        "fold_idx": 8,
        "checkpoint": "utooth-epoch=49-val_loss=0.1158.ckpt",
        "val_loss": 0.11882904171943665,
        "old_accuracy": 0.5611225962638855,
        "corrected_iou": 0.8164285719394684,
        "dice": 0.8914750218391418,
        "binary_iou": 0.790817379951477,
        "original_reported_accu": 0.6403077840805054,
        "original_reported_loss": 0.11578249931335449
      },
      {
        "fold_idx": 9,
        "checkpoint": "utooth-epoch=42-val_loss=0.1000.ckpt",
        "val_loss": 0.10086160898208618,
        "old_accuracy": 0.5479693412780762,
        "corrected_iou": 0.8219340145587921,
        "dice": 0.901593804359436,
        "binary_iou": 0.8230095505714417,
        "original_reported_accu": 0.6690560579299927,
        "original_reported_loss": 0.0999535322189331
      }
    ]
  },
  {
    "experiment": "utooth_10f_v4",
    "n_folds": 10,
    "metrics": {
      "corrected_iou": {
        "mean": 0.7422322432200115,
        "std": 0.07045593110666057,
        "min": 0.6111748516559601,
        "max": 0.8311178088188171
      },
      "dice": {
        "mean": 0.8234523942073185,
        "std": 0.07270698771515574,
        "min": 0.6805354356765747,
        "max": 0.9073625405629476
      },
      "binary_iou": {
        "mean": 0.7482469042142232,
        "std": 0.07364463889850453,
        "min": 0.6059629718462626,
        "max": 0.8331664204597473
      },
      "old_accuracy": {
        "mean": 0.5793314228455226,
        "std": 0.02872469734182574,
        "min": 0.5456639726956686,
        "max": 0.6436610817909241
      }
    },
    "fold_results": [
      {
        "fold_idx": 0,
        "checkpoint": "utooth-epoch=45-val_loss=0.1435.ckpt",
        "val_loss": 0.1568009853363037,
        "old_accuracy": 0.5811406970024109,
        "corrected_iou": 0.7381534973780314,
        "dice": 0.8221624692281088,
        "binary_iou": 0.7354158759117126,
        "original_reported_accu": 0.6248473525047302,
        "original_reported_loss": 0.14345324039459229
      },
      {
        "fold_idx": 1,
        "checkpoint": "utooth-epoch=46-val_loss=0.3069.ckpt",
        "val_loss": 0.2798695166905721,
        "old_accuracy": 0.5966392954190572,
        "corrected_iou": 0.6512139638264974,
        "dice": 0.7261665463447571,
        "binary_iou": 0.6059629718462626,
        "original_reported_accu": 0.5877790451049805,
        "original_reported_loss": 0.3069162368774414
      },
      {
        "fold_idx": 2,
        "checkpoint": "utooth-epoch=42-val_loss=0.1418.ckpt",
        "val_loss": 0.1412052313486735,
        "old_accuracy": 0.5456639726956686,
        "corrected_iou": 0.7678121328353882,
        "dice": 0.8482469121615092,
        "binary_iou": 0.7667260964711508,
        "original_reported_accu": 0.6270825266838074,
        "original_reported_loss": 0.1418454647064209
      },
      {
        "fold_idx": 3,
        "checkpoint": "utooth-epoch=43-val_loss=0.2657.ckpt",
        "val_loss": 0.24223188559214273,
        "old_accuracy": 0.5479853550593058,
        "corrected_iou": 0.6111748516559601,
        "dice": 0.6805354356765747,
        "binary_iou": 0.6256173749764761,
        "original_reported_accu": 0.5527195930480957,
        "original_reported_loss": 0.2656528949737549
      },
      {
        "fold_idx": 4,
        "checkpoint": "utooth-epoch=43-val_loss=0.1085.ckpt",
        "val_loss": 0.11549874146779378,
        "old_accuracy": 0.5756834149360657,
        "corrected_iou": 0.8036803603172302,
        "dice": 0.8865713874499003,
        "binary_iou": 0.8094514012336731,
        "original_reported_accu": 0.5924150943756104,
        "original_reported_loss": 0.10847389698028564
      },
      {
        "fold_idx": 5,
        "checkpoint": "utooth-epoch=47-val_loss=0.1470.ckpt",
        "val_loss": 0.15528281529744467,
        "old_accuracy": 0.5990063150723776,
        "corrected_iou": 0.683967669804891,
        "dice": 0.7719006935755411,
        "binary_iou": 0.744596540927887,
        "original_reported_accu": 0.5964417457580566,
        "original_reported_loss": 0.14699941873550415
      },
      {
        "fold_idx": 6,
        "checkpoint": "utooth-epoch=41-val_loss=0.0975.ckpt",
        "val_loss": 0.09795522689819336,
        "old_accuracy": 0.5919776558876038,
        "corrected_iou": 0.8311178088188171,
        "dice": 0.9073625405629476,
        "binary_iou": 0.8313330014546713,
        "original_reported_accu": 0.6357517242431641,
        "original_reported_loss": 0.09745687246322632
      },
      {
        "fold_idx": 7,
        "checkpoint": "utooth-epoch=46-val_loss=0.1285.ckpt",
        "val_loss": 0.13491171598434448,
        "old_accuracy": 0.5523123145103455,
        "corrected_iou": 0.7673235734303793,
        "dice": 0.8649424115816752,
        "binary_iou": 0.763595978418986,
        "original_reported_accu": 0.6077484488487244,
        "original_reported_loss": 0.12848323583602905
      },
      {
        "fold_idx": 8,
        "checkpoint": "utooth-epoch=48-val_loss=0.0933.ckpt",
        "val_loss": 0.0932164192199707,
        "old_accuracy": 0.6436610817909241,
        "corrected_iou": 0.830464780330658,
        "dice": 0.9067597985267639,
        "binary_iou": 0.8331664204597473,
        "original_reported_accu": 0.6628873348236084,
        "original_reported_loss": 0.09328478574752808
      },
      {
        "fold_idx": 9,
        "checkpoint": "utooth-epoch=38-val_loss=0.1415.ckpt",
        "val_loss": 0.14016273617744446,
        "old_accuracy": 0.5592441260814667,
        "corrected_iou": 0.7374137938022614,
        "dice": 0.8198757469654083,
        "binary_iou": 0.7666033804416656,
        "original_reported_accu": 0.6093724966049194,
        "original_reported_loss": 0.1414628028869629
      }
    ]
  }
]